newick/__init__.py
newick/backend/__init__.py
newick/backend/nhx_util.py
newick/backend/node.py
newick/backend/path.py
newick/backend/tree.py
newick/backend/util_funcs.py
newick/backend/test/__init__.py
newick/backend/test/test_nhx_util.py
newick/backend/test/test_node.py
newick/backend/test/test_path.py
newick/backend/test/test_tree.py
newick/frontend/__init__.py
newick/frontend/very_basic.py
newick/frontend/test/__init__.py
newick/frontend/test/test_very_basic.py
newick_tree_builder-0.4.17.dist-info/LICENSE
newick_tree_builder-0.4.17.dist-info/METADATA
newick_tree_builder-0.4.17.dist-info/WHEEL
newick_tree_builder-0.4.17.dist-info/top_level.txt
newick_tree_builder-0.4.17.dist-info/RECORD
