Metadata-Version: 2.1
Name: newick-tree-builder
Version: 0.4.17
Summary: Small lib to generate newick trees. Comes with NHX and rudimentary hybridization capabilities.
Author-email: Nico Rittinghaus <nico@ritti.ng>
License: # Creative Commons CC0 1.0 Universal
Project-URL: Homepage, https://github.com/NiRit100/newick-tree-builder
Keywords: biology,newick,newick-format,new hampshire,tree,graph-theory,x-nh
Classifier: Programming Language :: Python
Classifier: Programming Language :: Python :: 3
Classifier: Development Status :: 4 - Beta
Classifier: Intended Audience :: Developers
Classifier: Intended Audience :: Science/Research
Classifier: License :: Public Domain
Classifier: Topic :: Scientific/Engineering :: Bio-Informatics
Requires-Python: >=3.9
License-File: LICENSE
Provides-Extra: dev
Requires-Dist: pip-tools ; extra == 'dev'
Requires-Dist: pytest ; extra == 'dev'
